setup.py
coupon_codes/__init__.py
coupon_codes/coupon_codes.py
coupon_codes.egg-info/PKG-INFO
coupon_codes.egg-info/SOURCES.txt
coupon_codes.egg-info/dependency_links.txt
coupon_codes.egg-info/pbr.json
coupon_codes.egg-info/top_level.txt