Metadata-Version: 1.0
Name: coupon-codes
Version: 0.1
Summary: A coupon code generation algorithm
Home-page: https://github.com/brett-patterson/coupon_codes
Author: Brett Patterson
Author-email: bmp2@rice.edu
License: UNKNOWN
Platform: UNKNOWN
